msecrets/__init__.py
msecrets/cli.py
msecrets-0.1.0.dist-info/METADATA
msecrets-0.1.0.dist-info/WHEEL
msecrets-0.1.0.dist-info/entry_points.txt
msecrets-0.1.0.dist-info/licenses/LICENSE
msecrets-0.1.0.dist-info/RECORD
